pygico_imagegen/__init__.py
pygico_imagegen/cli.py
pygico_imagegen/config.py
pygico_imagegen/content_analysis/blog_extractor.py
pygico_imagegen/content_analysis/prompt_generator.py
pygico_imagegen/image_generation/comfy_interface.py
pygico_imagegen/image_processing/gimp_executor.py
pygico_imagegen/utils/config_manager.py
pygico_imagegen-0.1.5.dist-info/METADATA
pygico_imagegen-0.1.5.dist-info/WHEEL
pygico_imagegen-0.1.5.dist-info/entry_points.txt
pygico_imagegen-0.1.5.dist-info/top_level.txt
pygico_imagegen-0.1.5.dist-info/RECORD
