Metadata-Version: 2.1
Name: pygico-imagegen
Version: 0.1.5
Summary: Python, GIMP, and ComfyUI based image generation and text addition tool
Author-email: Your Name <your.email@example.com>
License: MIT
Classifier: Development Status :: 3 - Alpha
Classifier: Intended Audience :: Developers
Classifier: License :: OSI Approved :: MIT License
Classifier: Operating System :: OS Independent
Classifier: Programming Language :: Python :: 3
Classifier: Programming Language :: Python :: 3.8
Classifier: Programming Language :: Python :: 3.9
Classifier: Programming Language :: Python :: 3.10
Requires-Python: >=3.8.1
Requires-Dist: pygimp-labs <0.3.0,>=0.2.1
Requires-Dist: pillow <11.0.0,>=10.4.0
Requires-Dist: requests <3.0.0,>=2.32.3
Requires-Dist: python-dotenv <2.0.0,>=1.0.1
Requires-Dist: loguru <0.8.0,>=0.7.2
Requires-Dist: litellm <2.0.0,>=1.41.25
Requires-Dist: pydantic-settings <3.0.0,>=2.3.4
Provides-Extra: dev
Requires-Dist: pytest ; extra == 'dev'
Requires-Dist: black ; extra == 'dev'
Requires-Dist: isort ; extra == 'dev'
Requires-Dist: mypy ; extra == 'dev'
Requires-Dist: flake8 ; extra == 'dev'
Requires-Dist: sphinx ; extra == 'dev'
Requires-Dist: sphinx-rtd-theme ; extra == 'dev'
